{"wyi2fXiA56Y2kXcNRxASkw==":"mbr-506x337.jpg","Iwg8+poD6XEgdT3t3cDF8Q==":"mbr-506x358.jpeg","/jqnlRmpyfybkRqreDxmpg==":"mbr-506x345.jpg","ElSA5P+1F2anuVu/UQyVfg==":"mbr-506x337.png","kglYKv8x0zkEtaXecHxx4A==":"mbr-1-506x337.jpg","iGUTJ2xG2qEmsYM4A9aH/A==":"paystack-1076x314.png","OO8umO5+N38nU6ZKFoEaPw==":"google-zoom-1044x696.png","m9X6T7vI7EmGCUSA3Cn0EQ==":"background6.jpg","KfJEF7QvnGOtyDxfWD6pSA==":"mbr-1056x1056.png","gwqVLndrq/T4rf7rp55rrg==":"pay-1000x563.png","PN9nrCkSt/NIbikLMe9YNQ==":"pay-1-1000x563.png","eO4Wh0OjAWTnbu8rJXcd+A==":"pay%20per%20class-1000x563.png","5w1eh4s9pcVtNz4YAGY/Og==":"pay%20per%20class-1000x563.png","/zSBkFebCJ62TiByVeXIbg==":"pay%20per%20class-1000x563.png","+kFeWmCZyMkFPaQuM85mjQ==":"pay%20per%20class%203-600x338.png","YGmym5u66AkSNUULgnmLKg==":"pay%20per%20class%203-402x226.png","dsJJELn1mj2kQroX4K566Q==":"pay%20per%20class%203-402x226.png","zEqFqnsXEfqq2uysNpihXg==":"pay%20per%20class%203-402x226.png","gpdEdjccNnHJIS4T3CJCTQ==":"pay%20per%20class%204-402x226.png","Mik+f1s6WUV63nBj7sHHSA==":"pay%20per%20class%205-402x226.png","juYR0g4tPjuxRZvnjOEREA==":"pay%20per%20class%205-402x226.png","ucyn1n7Q4/UE6Vdk+IqV6Q==":"pay%20per%20class%205-402x226.png","/0UTafsF3D42a+2rjxAv5w==":"pay%20per%20class%205-402x226.png","NnCSIoObk6s0YhWLkA4CNQ==":"pay%20per%20class%205-600x338.png","9XglmpI1DLZAImj8q72jsA==":"pay%20per%20class%205-402x226.png","+FORlGkOKZi26EfKQjnzIQ==":"pay%20per%20class%205-402x226.png","Jow/k3IHzlu70hD7KXmaog==":"pay%20per%20month-402x226.png","Cy9xIV+Ymg2gBKj8b/OBLQ==":"pay%20per%20class%205-600x338.png","Ofc16d//fhmzqsXPEKJYaw==":"favicon-128x87.png","w7jztH9GXEb2f2FMFey8iw==":"mbr-240x360.jpeg","Twc7kW0ImmpgrgEeF1p17w==":"mbr-240x300.jpg","Tur9Oxffm0//c11sywBjfw==":"mbr-240x300.jpeg","Q1+TQMnisJHCzNK6lNtA4g==":"mbr-240x160.jpeg","hUl7X+5jxW41AXGwtf2dKw==":"mbr-1076x377.png","TGRzC0ep+m3qegyaOhZDHg==":"mbr-1456x861.jpg"}